gatfilter/__init__.py
gatfilter/gatfilter.py
gatfilter-0.1.0.dist-info/LICENSE
gatfilter-0.1.0.dist-info/METADATA
gatfilter-0.1.0.dist-info/WHEEL
gatfilter-0.1.0.dist-info/top_level.txt
gatfilter-0.1.0.dist-info/RECORD
